pythermodb_settings/__init__.py
pythermodb_settings/app.py
pythermodb_settings/configs/__init__.py
pythermodb_settings/configs/about.py
pythermodb_settings/models/__init__.py
pythermodb_settings/models/components.py
pythermodb_settings/models/conditions.py
pythermodb_settings/models/configs.py
pythermodb_settings/models/references.py
pythermodb_settings/models/rules.py
pythermodb_settings/models/source.py
pythermodb_settings/references/__init__.py
pythermodb_settings/references/component_extractor.py
pythermodb_settings/references/main.py
pythermodb_settings/references/yaml_extractor.py
pythermodb_settings/utils/__init__.py
pythermodb_settings/utils/component_utils.py
pythermodb_settings/utils/tools.py
pythermodb_settings-0.2.3.dist-info/licenses/LICENSE
pythermodb_settings-0.2.3.dist-info/METADATA
pythermodb_settings-0.2.3.dist-info/WHEEL
pythermodb_settings-0.2.3.dist-info/top_level.txt
pythermodb_settings-0.2.3.dist-info/RECORD
