Metadata-Version: 2.4
Name: pythermodb-settings
Version: 0.2.3
Summary: PyThermoDB Settings is a Python package that acts as an interface between PyThermDB and other applications, providing robust, Pydantic-based data models and configuration structures for managing thermodynamic database (ThermoDB) settings.
Author-email: Sina Gilassi <sina.gilassi@gmail.com>
License-Expression: MIT
Project-URL: Homepage, https://github.com/sinagilassi/PyThermoDB-Settings
Project-URL: Tracker, https://github.com/sinagilassi/PyThermoDB-Settings/issues
Classifier: Programming Language :: Python :: 3.11
Classifier: Operating System :: OS Independent
Requires-Python: >=3.11
License-File: LICENSE
Requires-Dist: pydantic>=2.11.7
Requires-Dist: pydantic-settings>=2.10.1
Requires-Dist: pyyaml>=6.0.3
Dynamic: license-file
